CHANGES.rst
LICENSE.txt
MANIFEST.in
README.rst
distribute_setup.py
setup.py
scss_tools/__init__.py
scss_tools/command.py
scss_tools/compiler.py
scss_tools/monitor.py
scss_tools.egg-info/PKG-INFO
scss_tools.egg-info/SOURCES.txt
scss_tools.egg-info/dependency_links.txt
scss_tools.egg-info/entry_points.txt
scss_tools.egg-info/not-zip-safe
scss_tools.egg-info/requires.txt
scss_tools.egg-info/top_level.txt
scss_tools/scss/blueprint/_buttons.scss
scss_tools/scss/blueprint/_colors.scss
scss_tools/scss/blueprint/_debug.scss
scss_tools/scss/blueprint/_fancy-type.scss
scss_tools/scss/blueprint/_form.scss
scss_tools/scss/blueprint/_grid.scss
scss_tools/scss/blueprint/_ie.scss
scss_tools/scss/blueprint/_interaction.scss
scss_tools/scss/blueprint/_link-icons.scss
scss_tools/scss/blueprint/_liquid.scss
scss_tools/scss/blueprint/_print.scss
scss_tools/scss/blueprint/_reset.scss
scss_tools/scss/blueprint/_rtl.scss
scss_tools/scss/blueprint/_scaffolding.scss
scss_tools/scss/blueprint/_typography.scss
scss_tools/scss/blueprint/_utilities.scss
scss_tools/scss/blueprint/reset/_utilities.scss
scss_tools/scss/compass/_css3.scss
scss_tools/scss/compass/_layout.scss
scss_tools/scss/compass/_reset-legacy.scss
scss_tools/scss/compass/_reset.scss
scss_tools/scss/compass/_support.scss
scss_tools/scss/compass/_typography.scss
scss_tools/scss/compass/_utilities.scss
scss_tools/scss/compass/css3/_appearance.scss
scss_tools/scss/compass/css3/_background-clip.scss
scss_tools/scss/compass/css3/_background-origin.scss
scss_tools/scss/compass/css3/_background-size.scss
scss_tools/scss/compass/css3/_border-radius.scss
scss_tools/scss/compass/css3/_box-shadow.scss
scss_tools/scss/compass/css3/_box-sizing.scss
scss_tools/scss/compass/css3/_box.scss
scss_tools/scss/compass/css3/_columns.scss
scss_tools/scss/compass/css3/_filter.scss
scss_tools/scss/compass/css3/_font-face.scss
scss_tools/scss/compass/css3/_gradient.scss
scss_tools/scss/compass/css3/_hyphenation.scss
scss_tools/scss/compass/css3/_images.scss
scss_tools/scss/compass/css3/_inline-block.scss
scss_tools/scss/compass/css3/_opacity.scss
scss_tools/scss/compass/css3/_pie.scss
scss_tools/scss/compass/css3/_regions.scss
scss_tools/scss/compass/css3/_shared.scss
