Metadata-Version: 1.1
Name: scss-tools
Version: 0.1.1
Summary: A bundle of tools for making web development with SCSS in Python much easier
Home-page: https://bitbucket.org/victorlin/scss_tools
Author: Victor Lin
Author-email: bornstub@gmail.com
License: UNKNOWN
Keywords: css oocss xcss sass scss less precompiler monitor
Platform: UNKNOWN
Classifier: Development Status :: 5 - Production/Stable
Classifier: Intended Audience :: Developers
Classifier: License :: OSI Approved :: MIT License
Classifier: Operating System :: OS Independent
Classifier: Programming Language :: Python
Classifier: Programming Language :: Python :: 3
Classifier: Topic :: Software Development :: Code Generators
Classifier: Topic :: Text Processing :: Markup
Classifier: Topic :: Software Development :: Libraries :: Python Modules
Classifier: Environment :: Console
